{"box_data": [{"position": {"minX": 306.75, "minY": 388.25, "maxX": 322.25, "maxY": 412.25}, "class_id": 1, "box_caption": "defect 0.252", "scores": {"class_score": 0.251708984375}, "domain": "pixel"}, {"position": {"minX": 174.75, "minY": 266.75, "maxX": 198.5, "maxY": 290.75}, "class_id": 1, "box_caption": "defect 0.233", "scores": {"class_score": 0.232666015625}, "domain": "pixel"}, {"position": {"minX": 167.0, "minY": 259.0, "maxX": 201.5, "maxY": 301.5}, "class_id": 1, "box_caption": "defect 0.204", "scores": {"class_score": 0.2037353515625}, "domain": "pixel"}, {"position": {"minX": 167.0, "minY": 259.0, "maxX": 201.5, "maxY": 301.5}, "class_id": 0, "box_caption": "imbalance 0.155", "scores": {"class_score": 0.155029296875}, "domain": "pixel"}, {"position": {"minX": 322.0, "minY": 17.546875, "maxX": 345.0, "maxY": 46.6875}, "class_id": 1, "box_caption": "defect 0.151", "scores": {"class_score": 0.1505126953125}, "domain": "pixel"}, {"position": {"minX": 174.75, "minY": 266.75, "maxX": 198.5, "maxY": 290.75}, "class_id": 0, "box_caption": "imbalance 0.093", "scores": {"class_score": 0.09326171875}, "domain": "pixel"}, {"position": {"minX": 548.5, "minY": 616.5, "maxX": 591.5, "maxY": 650.5}, "class_id": 1, "box_caption": "defect 0.084", "scores": {"class_score": 0.083740234375}, "domain": "pixel"}, {"position": {"minX": 369.0, "minY": 556.0, "maxX": 451.0, "maxY": 654.0}, "class_id": 1, "box_caption": "defect 0.072", "scores": {"class_score": 0.072021484375}, "domain": "pixel"}, {"position": {"minX": 48.75, "minY": 269.5, "maxX": 496.75, "maxY": 617.5}, "class_id": 1, "box_caption": "defect 0.062", "scores": {"class_score": 0.062347412109375}, "domain": "pixel"}, {"position": {"minX": 262.5, "minY": 614.0, "maxX": 284.0, "maxY": 643.0}, "class_id": 1, "box_caption": "defect 0.057", "scores": {"class_score": 0.057373046875}, "domain": "pixel"}, {"position": {"minX": 325.75, "minY": 21.296875, "maxX": 344.75, "maxY": 38.9375}, "class_id": 1, "box_caption": "defect 0.055", "scores": {"class_score": 0.05517578125}, "domain": "pixel"}, {"position": {"minX": 328.5, "minY": 12.84375, "maxX": 342.0, "maxY": 46.625}, "class_id": 1, "box_caption": "defect 0.055", "scores": {"class_score": 0.055084228515625}, "domain": "pixel"}, {"position": {"minX": 527.0, "minY": 16.125, "maxX": 540.0, "maxY": 39.875}, "class_id": 1, "box_caption": "defect 0.055", "scores": {"class_score": 0.055023193359375}, "domain": "pixel"}, {"position": {"minX": 361.5, "minY": 578.5, "maxX": 450.5, "maxY": 631.5}, "class_id": 1, "box_caption": "defect 0.054", "scores": {"class_score": 0.05377197265625}, "domain": "pixel"}, {"position": {"minX": 547.0, "minY": 598.5, "maxX": 593.0, "maxY": 660.5}, "class_id": 1, "box_caption": "defect 0.047", "scores": {"class_score": 0.0469970703125}, "domain": "pixel"}, {"position": {"minX": 189.25, "minY": 51.75, "maxX": 214.5, "maxY": 83.875}, "class_id": 1, "box_caption": "defect 0.047", "scores": {"class_score": 0.04693603515625}, "domain": "pixel"}, {"position": {"minX": 88.875, "minY": 305.5, "maxX": 138.875, "maxY": 338.5}, "class_id": 1, "box_caption": "defect 0.046", "scores": {"class_score": 0.04632568359375}, "domain": "pixel"}, {"position": {"minX": 465.75, "minY": 593.5, "maxX": 583.0, "maxY": 652.5}, "class_id": 1, "box_caption": "defect 0.046", "scores": {"class_score": 0.0458984375}, "domain": "pixel"}, {"position": {"minX": 77.8125, "minY": 299.0, "maxX": 135.75, "maxY": 347.0}, "class_id": 1, "box_caption": "defect 0.045", "scores": {"class_score": 0.045196533203125}, "domain": "pixel"}, {"position": {"minX": 306.75, "minY": 388.25, "maxX": 322.25, "maxY": 412.25}, "class_id": 0, "box_caption": "imbalance 0.045", "scores": {"class_score": 0.04461669921875}, "domain": "pixel"}, {"position": {"minX": 169.375, "minY": 270.0, "maxX": 201.875, "maxY": 296.0}, "class_id": 1, "box_caption": "defect 0.044", "scores": {"class_score": 0.044342041015625}, "domain": "pixel"}, {"position": {"minX": 384.5, "minY": 354.5, "maxX": 396.0, "maxY": 370.0}, "class_id": 1, "box_caption": "defect 0.044", "scores": {"class_score": 0.044097900390625}, "domain": "pixel"}, {"position": {"minX": 173.25, "minY": 254.0, "maxX": 209.0, "maxY": 294.5}, "class_id": 1, "box_caption": "defect 0.042", "scores": {"class_score": 0.04217529296875}, "domain": "pixel"}, {"position": {"minX": 308.25, "minY": 392.75, "maxX": 320.25, "maxY": 408.75}, "class_id": 1, "box_caption": "defect 0.038", "scores": {"class_score": 0.037689208984375}, "domain": "pixel"}, {"position": {"minX": 513.5, "minY": 605.5, "maxX": 588.5, "maxY": 661.5}, "class_id": 1, "box_caption": "defect 0.037", "scores": {"class_score": 0.037109375}, "domain": "pixel"}, {"position": {"minX": 278.0, "minY": 511.25, "maxX": 292.5, "maxY": 549.0}, "class_id": 1, "box_caption": "defect 0.037", "scores": {"class_score": 0.03662109375}, "domain": "pixel"}, {"position": {"minX": 422.25, "minY": 108.375, "maxX": 520.0, "maxY": 208.625}, "class_id": 1, "box_caption": "defect 0.035", "scores": {"class_score": 0.03460693359375}, "domain": "pixel"}, {"position": {"minX": 88.875, "minY": 305.5, "maxX": 138.875, "maxY": 338.5}, "class_id": 0, "box_caption": "imbalance 0.035", "scores": {"class_score": 0.034515380859375}, "domain": "pixel"}, {"position": {"minX": 295.75, "minY": 572.0, "maxX": 444.25, "maxY": 641.0}, "class_id": 1, "box_caption": "defect 0.034", "scores": {"class_score": 0.033782958984375}, "domain": "pixel"}, {"position": {"minX": 447.0, "minY": 596.5, "maxX": 558.0, "maxY": 639.5}, "class_id": 1, "box_caption": "defect 0.033", "scores": {"class_score": 0.0333251953125}, "domain": "pixel"}, {"position": {"minX": 121.625, "minY": 293.25, "maxX": 144.125, "maxY": 322.25}, "class_id": 1, "box_caption": "defect 0.033", "scores": {"class_score": 0.032989501953125}, "domain": "pixel"}, {"position": {"minX": 171.5, "minY": 509.75, "maxX": 183.5, "maxY": 519.5}, "class_id": 1, "box_caption": "defect 0.033", "scores": {"class_score": 0.03253173828125}, "domain": "pixel"}, {"position": {"minX": 409.25, "minY": 556.0, "maxX": 448.75, "maxY": 604.0}, "class_id": 1, "box_caption": "defect 0.032", "scores": {"class_score": 0.03155517578125}, "domain": "pixel"}, {"position": {"minX": 556.0, "minY": 612.0, "maxX": 598.0, "maxY": 660.0}, "class_id": 1, "box_caption": "defect 0.030", "scores": {"class_score": 0.030426025390625}, "domain": "pixel"}, {"position": {"minX": 17.71875, "minY": 632.0, "maxX": 36.96875, "maxY": 657.0}, "class_id": 1, "box_caption": "defect 0.030", "scores": {"class_score": 0.0298309326171875}, "domain": "pixel"}, {"position": {"minX": 87.1875, "minY": 294.5, "maxX": 149.25, "maxY": 345.5}, "class_id": 0, "box_caption": "imbalance 0.029", "scores": {"class_score": 0.0292510986328125}, "domain": "pixel"}, {"position": {"minX": 524.5, "minY": 610.0, "maxX": 616.5, "maxY": 661.0}, "class_id": 1, "box_caption": "defect 0.029", "scores": {"class_score": 0.02862548828125}, "domain": "pixel"}, {"position": {"minX": 432.75, "minY": 104.0625, "maxX": 487.25, "maxY": 195.0}, "class_id": 1, "box_caption": "defect 0.028", "scores": {"class_score": 0.0281829833984375}, "domain": "pixel"}, {"position": {"minX": 128.125, "minY": 297.25, "maxX": 142.875, "maxY": 317.75}, "class_id": 1, "box_caption": "defect 0.028", "scores": {"class_score": 0.027801513671875}, "domain": "pixel"}, {"position": {"minX": 365.0, "minY": 556.5, "maxX": 451.0, "maxY": 667.5}, "class_id": 0, "box_caption": "imbalance 0.027", "scores": {"class_score": 0.02716064453125}, "domain": "pixel"}, {"position": {"minX": 37.75, "minY": 112.0, "maxX": 590.0, "maxY": 678.5}, "class_id": 1, "box_caption": "defect 0.027", "scores": {"class_score": 0.0269622802734375}, "domain": "pixel"}, {"position": {"minX": 199.875, "minY": 180.875, "maxX": 664.5, "maxY": 619.0}, "class_id": 1, "box_caption": "defect 0.027", "scores": {"class_score": 0.02679443359375}, "domain": "pixel"}, {"position": {"minX": 84.75, "minY": 311.75, "maxX": 102.5, "maxY": 346.25}, "class_id": 1, "box_caption": "defect 0.025", "scores": {"class_score": 0.0252838134765625}, "domain": "pixel"}, {"position": {"minX": 524.5, "minY": 13.828125, "maxX": 545.5, "maxY": 46.3125}, "class_id": 1, "box_caption": "defect 0.025", "scores": {"class_score": 0.0245513916015625}, "domain": "pixel"}, {"position": {"minX": 89.6875, "minY": 296.25, "maxX": 153.375, "maxY": 349.75}, "class_id": 1, "box_caption": "defect 0.024", "scores": {"class_score": 0.02447509765625}, "domain": "pixel"}, {"position": {"minX": 322.0, "minY": 17.546875, "maxX": 345.0, "maxY": 46.6875}, "class_id": 0, "box_caption": "imbalance 0.024", "scores": {"class_score": 0.024169921875}, "domain": "pixel"}, {"position": {"minX": 548.5, "minY": 616.5, "maxX": 591.5, "maxY": 650.5}, "class_id": 0, "box_caption": "imbalance 0.022", "scores": {"class_score": 0.0223388671875}, "domain": "pixel"}, {"position": {"minX": 309.75, "minY": 390.75, "maxX": 319.25, "maxY": 413.25}, "class_id": 1, "box_caption": "defect 0.022", "scores": {"class_score": 0.0217132568359375}, "domain": "pixel"}, {"position": {"minX": 385.5, "minY": 354.0, "maxX": 395.0, "maxY": 366.0}, "class_id": 1, "box_caption": "defect 0.021", "scores": {"class_score": 0.0214385986328125}, "domain": "pixel"}, {"position": {"minX": 25.625, "minY": 389.5, "maxX": 470.5, "maxY": 609.5}, "class_id": 1, "box_caption": "defect 0.021", "scores": {"class_score": 0.0213775634765625}, "domain": "pixel"}, {"position": {"minX": 542.0, "minY": 610.5, "maxX": 582.0, "maxY": 658.5}, "class_id": 1, "box_caption": "defect 0.020", "scores": {"class_score": 0.0204010009765625}, "domain": "pixel"}, {"position": {"minX": 173.25, "minY": 254.0, "maxX": 209.0, "maxY": 294.5}, "class_id": 0, "box_caption": "imbalance 0.020", "scores": {"class_score": 0.0200958251953125}, "domain": "pixel"}, {"position": {"minX": 183.25, "minY": 47.6875, "maxX": 212.75, "maxY": 91.3125}, "class_id": 1, "box_caption": "defect 0.020", "scores": {"class_score": 0.01995849609375}, "domain": "pixel"}, {"position": {"minX": 121.625, "minY": 293.25, "maxX": 144.125, "maxY": 322.25}, "class_id": 0, "box_caption": "imbalance 0.020", "scores": {"class_score": 0.01953125}, "domain": "pixel"}, {"position": {"minX": 202.25, "minY": 90.0, "maxX": 604.0, "maxY": 445.5}, "class_id": 1, "box_caption": "defect 0.019", "scores": {"class_score": 0.0194854736328125}, "domain": "pixel"}, {"position": {"minX": 67.6875, "minY": 287.25, "maxX": 157.75, "maxY": 346.25}, "class_id": 1, "box_caption": "defect 0.019", "scores": {"class_score": 0.0193328857421875}, "domain": "pixel"}, {"position": {"minX": 242.5, "minY": 578.0, "maxX": 429.0, "maxY": 637.0}, "class_id": 1, "box_caption": "defect 0.019", "scores": {"class_score": 0.018829345703125}, "domain": "pixel"}, {"position": {"minX": 301.75, "minY": 18.515625, "maxX": 339.25, "maxY": 63.9375}, "class_id": 1, "box_caption": "defect 0.019", "scores": {"class_score": 0.018768310546875}, "domain": "pixel"}, {"position": {"minX": 369.75, "minY": 127.5, "maxX": 614.0, "maxY": 610.0}, "class_id": 1, "box_caption": "defect 0.019", "scores": {"class_score": 0.0186004638671875}, "domain": "pixel"}, {"position": {"minX": 351.5, "minY": 560.0, "maxX": 434.0, "maxY": 668.0}, "class_id": 1, "box_caption": "defect 0.018", "scores": {"class_score": 0.017913818359375}, "domain": "pixel"}, {"position": {"minX": 189.25, "minY": 51.75, "maxX": 214.5, "maxY": 83.875}, "class_id": 0, "box_caption": "imbalance 0.018", "scores": {"class_score": 0.0177001953125}, "domain": "pixel"}, {"position": {"minX": 256.25, "minY": 316.75, "maxX": 621.0, "maxY": 611.0}, "class_id": 1, "box_caption": "defect 0.018", "scores": {"class_score": 0.0177001953125}, "domain": "pixel"}, {"position": {"minX": 18.28125, "minY": 622.0, "maxX": 39.84375, "maxY": 660.0}, "class_id": 1, "box_caption": "defect 0.018", "scores": {"class_score": 0.0175628662109375}, "domain": "pixel"}, {"position": {"minX": 237.5, "minY": 119.8125, "maxX": 584.5, "maxY": 353.5}, "class_id": 1, "box_caption": "defect 0.018", "scores": {"class_score": 0.0175018310546875}, "domain": "pixel"}, {"position": {"minX": 86.8125, "minY": 309.25, "maxX": 99.4375, "maxY": 339.75}, "class_id": 1, "box_caption": "defect 0.017", "scores": {"class_score": 0.016571044921875}, "domain": "pixel"}, {"position": {"minX": 454.75, "minY": 592.0, "maxX": 556.0, "maxY": 650.0}, "class_id": 0, "box_caption": "imbalance 0.016", "scores": {"class_score": 0.0162200927734375}, "domain": "pixel"}, {"position": {"minX": 128.125, "minY": 297.25, "maxX": 142.875, "maxY": 317.75}, "class_id": 0, "box_caption": "imbalance 0.015", "scores": {"class_score": 0.015380859375}, "domain": "pixel"}, {"position": {"minX": 416.0, "minY": 330.5, "maxX": 647.0, "maxY": 612.0}, "class_id": 1, "box_caption": "defect 0.015", "scores": {"class_score": 0.0148773193359375}, "domain": "pixel"}, {"position": {"minX": 13.46875, "minY": 608.0, "maxX": 34.625, "maxY": 663.0}, "class_id": 1, "box_caption": "defect 0.014", "scores": {"class_score": 0.01441192626953125}, "domain": "pixel"}, {"position": {"minX": 548.0, "minY": 161.0, "maxX": 594.0, "maxY": 238.0}, "class_id": 0, "box_caption": "imbalance 0.014", "scores": {"class_score": 0.01430511474609375}, "domain": "pixel"}, {"position": {"minX": 348.25, "minY": 119.75, "maxX": 579.5, "maxY": 477.75}, "class_id": 1, "box_caption": "defect 0.014", "scores": {"class_score": 0.0140838623046875}, "domain": "pixel"}, {"position": {"minX": 378.25, "minY": 595.0, "maxX": 394.25, "maxY": 626.0}, "class_id": 1, "box_caption": "defect 0.014", "scores": {"class_score": 0.0140228271484375}, "domain": "pixel"}, {"position": {"minX": 267.75, "minY": 614.5, "maxX": 291.25, "maxY": 642.5}, "class_id": 1, "box_caption": "defect 0.014", "scores": {"class_score": 0.01401519775390625}, "domain": "pixel"}, {"position": {"minX": 75.6875, "minY": 306.5, "maxX": 118.0625, "maxY": 345.0}, "class_id": 1, "box_caption": "defect 0.014", "scores": {"class_score": 0.01393890380859375}, "domain": "pixel"}, {"position": {"minX": 446.5, "minY": 93.75, "maxX": 508.5, "maxY": 213.5}, "class_id": 1, "box_caption": "defect 0.014", "scores": {"class_score": 0.0135345458984375}, "domain": "pixel"}, {"position": {"minX": 422.0, "minY": 599.5, "maxX": 511.5, "maxY": 643.5}, "class_id": 1, "box_caption": "defect 0.013", "scores": {"class_score": 0.0134124755859375}, "domain": "pixel"}, {"position": {"minX": 23.1875, "minY": 641.5, "maxX": 33.3125, "maxY": 653.5}, "class_id": 1, "box_caption": "defect 0.013", "scores": {"class_score": 0.01340484619140625}, "domain": "pixel"}, {"position": {"minX": 301.25, "minY": 391.25, "maxX": 326.25, "maxY": 409.75}, "class_id": 0, "box_caption": "imbalance 0.013", "scores": {"class_score": 0.013336181640625}, "domain": "pixel"}, {"position": {"minX": 512.0, "minY": 250.5, "maxX": 569.0, "maxY": 314.5}, "class_id": 1, "box_caption": "defect 0.013", "scores": {"class_score": 0.01329803466796875}, "domain": "pixel"}, {"position": {"minX": 328.5, "minY": 12.84375, "maxX": 342.0, "maxY": 46.625}, "class_id": 0, "box_caption": "imbalance 0.013", "scores": {"class_score": 0.01325225830078125}, "domain": "pixel"}, {"position": {"minX": 537.0, "minY": 618.0, "maxX": 627.0, "maxY": 656.0}, "class_id": 1, "box_caption": "defect 0.013", "scores": {"class_score": 0.01320648193359375}, "domain": "pixel"}, {"position": {"minX": 105.0625, "minY": 281.0, "maxX": 148.0, "maxY": 329.0}, "class_id": 1, "box_caption": "defect 0.013", "scores": {"class_score": 0.0130462646484375}, "domain": "pixel"}, {"position": {"minX": 318.0, "minY": 23.5625, "maxX": 353.0, "maxY": 48.0625}, "class_id": 1, "box_caption": "defect 0.013", "scores": {"class_score": 0.0128326416015625}, "domain": "pixel"}, {"position": {"minX": 268.5, "minY": 519.5, "maxX": 301.0, "maxY": 545.5}, "class_id": 1, "box_caption": "defect 0.013", "scores": {"class_score": 0.01268768310546875}, "domain": "pixel"}, {"position": {"minX": 163.375, "minY": 506.75, "maxX": 191.125, "maxY": 527.5}, "class_id": 1, "box_caption": "defect 0.013", "scores": {"class_score": 0.0126190185546875}, "domain": "pixel"}, {"position": {"minX": 116.375, "minY": -3.25, "maxX": 624.5, "maxY": 600.0}, "class_id": 1, "box_caption": "defect 0.013", "scores": {"class_score": 0.0125885009765625}, "domain": "pixel"}, {"position": {"minX": 301.75, "minY": 18.515625, "maxX": 339.25, "maxY": 63.9375}, "class_id": 0, "box_caption": "imbalance 0.012", "scores": {"class_score": 0.0124969482421875}, "domain": "pixel"}, {"position": {"minX": 259.25, "minY": 607.0, "maxX": 299.75, "maxY": 648.0}, "class_id": 1, "box_caption": "defect 0.012", "scores": {"class_score": 0.012451171875}, "domain": "pixel"}, {"position": {"minX": 67.6875, "minY": 287.25, "maxX": 157.75, "maxY": 346.25}, "class_id": 0, "box_caption": "imbalance 0.012", "scores": {"class_score": 0.011749267578125}, "domain": "pixel"}, {"position": {"minX": 61.125, "minY": 80.375, "maxX": 351.5, "maxY": 452.5}, "class_id": 1, "box_caption": "defect 0.012", "scores": {"class_score": 0.01174163818359375}, "domain": "pixel"}, {"position": {"minX": 268.5, "minY": 22.0625, "maxX": 275.5, "maxY": 47.4375}, "class_id": 1, "box_caption": "defect 0.012", "scores": {"class_score": 0.0117340087890625}, "domain": "pixel"}, {"position": {"minX": 316.75, "minY": 20.65625, "maxX": 350.25, "maxY": 61.40625}, "class_id": 1, "box_caption": "defect 0.012", "scores": {"class_score": 0.01161956787109375}, "domain": "pixel"}, {"position": {"minX": 295.5, "minY": 393.5, "maxX": 329.0, "maxY": 410.0}, "class_id": 1, "box_caption": "defect 0.011", "scores": {"class_score": 0.0113067626953125}, "domain": "pixel"}, {"position": {"minX": 454.0, "minY": 585.5, "maxX": 555.5, "maxY": 660.5}, "class_id": 1, "box_caption": "defect 0.011", "scores": {"class_score": 0.0111846923828125}, "domain": "pixel"}, {"position": {"minX": 78.75, "minY": 135.875, "maxX": 415.25, "maxY": 603.0}, "class_id": 1, "box_caption": "defect 0.011", "scores": {"class_score": 0.01116943359375}, "domain": "pixel"}, {"position": {"minX": 447.75, "minY": 165.75, "maxX": 510.75, "maxY": 238.0}, "class_id": 1, "box_caption": "defect 0.011", "scores": {"class_score": 0.01114654541015625}, "domain": "pixel"}, {"position": {"minX": 326.5, "minY": 17.6875, "maxX": 344.5, "maxY": 39.8125}, "class_id": 0, "box_caption": "imbalance 0.011", "scores": {"class_score": 0.01113128662109375}, "domain": "pixel"}, {"position": {"minX": 422.25, "minY": 108.375, "maxX": 520.0, "maxY": 208.625}, "class_id": 0, "box_caption": "imbalance 0.011", "scores": {"class_score": 0.01111602783203125}, "domain": "pixel"}, {"position": {"minX": 46.25, "minY": 70.875, "maxX": 499.25, "maxY": 400.0}, "class_id": 1, "box_caption": "defect 0.011", "scores": {"class_score": 0.0111083984375}, "domain": "pixel"}, {"position": {"minX": 304.5, "minY": 52.375, "maxX": 387.0, "maxY": 83.625}, "class_id": 0, "box_caption": "imbalance 0.011", "scores": {"class_score": 0.01104736328125}, "domain": "pixel"}, {"position": {"minX": 188.25, "minY": 57.90625, "maxX": 213.75, "maxY": 94.25}, "class_id": 1, "box_caption": "defect 0.011", "scores": {"class_score": 0.01073455810546875}, "domain": "pixel"}, {"position": {"minX": 531.5, "minY": 17.6875, "maxX": 539.5, "maxY": 38.3125}, "class_id": 1, "box_caption": "defect 0.011", "scores": {"class_score": 0.0105438232421875}, "domain": "pixel"}, {"position": {"minX": 168.125, "minY": 245.375, "maxX": 214.375, "maxY": 301.0}, "class_id": 1, "box_caption": "defect 0.010", "scores": {"class_score": 0.010498046875}, "domain": "pixel"}, {"position": {"minX": 84.75, "minY": 311.75, "maxX": 102.5, "maxY": 346.25}, "class_id": 0, "box_caption": "imbalance 0.010", "scores": {"class_score": 0.0104827880859375}, "domain": "pixel"}, {"position": {"minX": 512.0, "minY": 250.5, "maxX": 569.0, "maxY": 314.5}, "class_id": 0, "box_caption": "imbalance 0.010", "scores": {"class_score": 0.0104522705078125}, "domain": "pixel"}, {"position": {"minX": 268.5, "minY": 519.5, "maxX": 301.0, "maxY": 545.5}, "class_id": 0, "box_caption": "imbalance 0.010", "scores": {"class_score": 0.0104217529296875}, "domain": "pixel"}, {"position": {"minX": 18.28125, "minY": 622.0, "maxX": 39.84375, "maxY": 660.0}, "class_id": 0, "box_caption": "imbalance 0.010", "scores": {"class_score": 0.010162353515625}, "domain": "pixel"}, {"position": {"minX": 391.0, "minY": 565.0, "maxX": 455.5, "maxY": 618.0}, "class_id": 1, "box_caption": "defect 0.010", "scores": {"class_score": 0.0101470947265625}, "domain": "pixel"}, {"position": {"minX": 262.5, "minY": 614.0, "maxX": 284.0, "maxY": 643.0}, "class_id": 0, "box_caption": "imbalance 0.010", "scores": {"class_score": 0.01010894775390625}, "domain": "pixel"}, {"position": {"minX": 571.5, "minY": 604.0, "maxX": 649.5, "maxY": 664.0}, "class_id": 1, "box_caption": "defect 0.010", "scores": {"class_score": 0.01010894775390625}, "domain": "pixel"}, {"position": {"minX": 308.25, "minY": 24.453125, "maxX": 334.25, "maxY": 68.4375}, "class_id": 1, "box_caption": "defect 0.010", "scores": {"class_score": 0.01006317138671875}, "domain": "pixel"}, {"position": {"minX": 467.25, "minY": 166.25, "maxX": 504.25, "maxY": 233.5}, "class_id": 1, "box_caption": "defect 0.010", "scores": {"class_score": 0.0100555419921875}, "domain": "pixel"}, {"position": {"minX": 409.25, "minY": 556.0, "maxX": 448.75, "maxY": 604.0}, "class_id": 0, "box_caption": "imbalance 0.010", "scores": {"class_score": 0.0100250244140625}, "domain": "pixel"}, {"position": {"minX": 375.75, "minY": 130.75, "maxX": 567.0, "maxY": 354.5}, "class_id": 1, "box_caption": "defect 0.010", "scores": {"class_score": 0.01001739501953125}, "domain": "pixel"}, {"position": {"minX": 104.375, "minY": 288.75, "maxX": 149.125, "maxY": 335.25}, "class_id": 0, "box_caption": "imbalance 0.010", "scores": {"class_score": 0.00989532470703125}, "domain": "pixel"}, {"position": {"minX": 529.5, "minY": 266.5, "maxX": 565.5, "maxY": 312.5}, "class_id": 1, "box_caption": "defect 0.010", "scores": {"class_score": 0.0097198486328125}, "domain": "pixel"}, {"position": {"minX": 118.0625, "minY": 278.25, "maxX": 143.375, "maxY": 323.25}, "class_id": 1, "box_caption": "defect 0.010", "scores": {"class_score": 0.0096588134765625}, "domain": "pixel"}, {"position": {"minX": 619.0, "minY": 103.625, "maxX": 659.0, "maxY": 260.5}, "class_id": 1, "box_caption": "defect 0.010", "scores": {"class_score": 0.00965118408203125}, "domain": "pixel"}, {"position": {"minX": 60.375, "minY": 305.25, "maxX": 366.5, "maxY": 570.0}, "class_id": 1, "box_caption": "defect 0.010", "scores": {"class_score": 0.00955963134765625}, "domain": "pixel"}, {"position": {"minX": 623.0, "minY": 368.75, "maxX": 651.0, "maxY": 487.75}, "class_id": 1, "box_caption": "defect 0.009", "scores": {"class_score": 0.00948333740234375}, "domain": "pixel"}, {"position": {"minX": 425.5, "minY": 610.0, "maxX": 463.0, "maxY": 657.0}, "class_id": 1, "box_caption": "defect 0.009", "scores": {"class_score": 0.0093536376953125}, "domain": "pixel"}, {"position": {"minX": 124.125, "minY": 342.0, "maxX": 633.5, "maxY": 661.0}, "class_id": 1, "box_caption": "defect 0.009", "scores": {"class_score": 0.0093231201171875}, "domain": "pixel"}, {"position": {"minX": 142.125, "minY": 55.375, "maxX": 620.5, "maxY": 357.5}, "class_id": 1, "box_caption": "defect 0.009", "scores": {"class_score": 0.00921630859375}, "domain": "pixel"}, {"position": {"minX": 88.625, "minY": 303.5, "maxX": 121.25, "maxY": 348.5}, "class_id": 0, "box_caption": "imbalance 0.009", "scores": {"class_score": 0.0091400146484375}, "domain": "pixel"}, {"position": {"minX": 436.75, "minY": 102.875, "maxX": 536.5, "maxY": 307.0}, "class_id": 1, "box_caption": "defect 0.009", "scores": {"class_score": 0.00911712646484375}, "domain": "pixel"}, {"position": {"minX": 187.5, "minY": 48.625, "maxX": 222.0, "maxY": 77.0625}, "class_id": 1, "box_caption": "defect 0.009", "scores": {"class_score": 0.00910186767578125}, "domain": "pixel"}, {"position": {"minX": 166.625, "minY": 513.5, "maxX": 188.125, "maxY": 520.5}, "class_id": 1, "box_caption": "defect 0.009", "scores": {"class_score": 0.0090789794921875}, "domain": "pixel"}, {"position": {"minX": 426.5, "minY": 562.5, "maxX": 490.5, "maxY": 650.5}, "class_id": 1, "box_caption": "defect 0.009", "scores": {"class_score": 0.00904083251953125}, "domain": "pixel"}, {"position": {"minX": 421.5, "minY": 557.0, "maxX": 452.5, "maxY": 647.0}, "class_id": 1, "box_caption": "defect 0.009", "scores": {"class_score": 0.00893402099609375}, "domain": "pixel"}, {"position": {"minX": 404.25, "minY": 169.0, "maxX": 508.75, "maxY": 320.5}, "class_id": 1, "box_caption": "defect 0.009", "scores": {"class_score": 0.00888824462890625}, "domain": "pixel"}, {"position": {"minX": 308.25, "minY": 24.453125, "maxX": 334.25, "maxY": 68.4375}, "class_id": 0, "box_caption": "imbalance 0.009", "scores": {"class_score": 0.008697509765625}, "domain": "pixel"}, {"position": {"minX": 570.5, "minY": 256.25, "maxX": 590.5, "maxY": 281.75}, "class_id": 1, "box_caption": "defect 0.009", "scores": {"class_score": 0.0086822509765625}, "domain": "pixel"}, {"position": {"minX": 625.0, "minY": 100.25, "maxX": 654.0, "maxY": 230.25}, "class_id": 1, "box_caption": "defect 0.009", "scores": {"class_score": 0.00862884521484375}, "domain": "pixel"}, {"position": {"minX": 550.0, "minY": 161.25, "maxX": 587.0, "maxY": 217.0}, "class_id": 0, "box_caption": "imbalance 0.008", "scores": {"class_score": 0.00846099853515625}, "domain": "pixel"}, {"position": {"minX": 500.25, "minY": 217.25, "maxX": 574.0, "maxY": 317.75}, "class_id": 1, "box_caption": "defect 0.008", "scores": {"class_score": 0.00846099853515625}, "domain": "pixel"}, {"position": {"minX": 403.25, "minY": 123.125, "maxX": 511.75, "maxY": 261.0}, "class_id": 1, "box_caption": "defect 0.008", "scores": {"class_score": 0.00835418701171875}, "domain": "pixel"}, {"position": {"minX": 614.0, "minY": 427.0, "maxX": 655.0, "maxY": 580.5}, "class_id": 1, "box_caption": "defect 0.008", "scores": {"class_score": 0.008270263671875}, "domain": "pixel"}, {"position": {"minX": 304.5, "minY": 52.375, "maxX": 387.0, "maxY": 83.625}, "class_id": 1, "box_caption": "defect 0.008", "scores": {"class_score": 0.00823974609375}, "domain": "pixel"}, {"position": {"minX": 167.125, "minY": 279.0, "maxX": 193.875, "maxY": 295.0}, "class_id": 1, "box_caption": "defect 0.008", "scores": {"class_score": 0.00821685791015625}, "domain": "pixel"}, {"position": {"minX": 264.25, "minY": 14.96875, "maxX": 278.25, "maxY": 51.78125}, "class_id": 1, "box_caption": "defect 0.008", "scores": {"class_score": 0.0081787109375}, "domain": "pixel"}, {"position": {"minX": 566.5, "minY": 605.0, "maxX": 590.5, "maxY": 662.0}, "class_id": 1, "box_caption": "defect 0.008", "scores": {"class_score": 0.00815582275390625}, "domain": "pixel"}, {"position": {"minX": 17.71875, "minY": 632.0, "maxX": 36.96875, "maxY": 657.0}, "class_id": 0, "box_caption": "imbalance 0.008", "scores": {"class_score": 0.00814056396484375}, "domain": "pixel"}, {"position": {"minX": 563.0, "minY": 162.5, "maxX": 584.0, "maxY": 211.5}, "class_id": 1, "box_caption": "defect 0.008", "scores": {"class_score": 0.0080413818359375}, "domain": "pixel"}, {"position": {"minX": 482.75, "minY": 572.0, "maxX": 615.0, "maxY": 653.0}, "class_id": 1, "box_caption": "defect 0.008", "scores": {"class_score": 0.00795745849609375}, "domain": "pixel"}, {"position": {"minX": 475.5, "minY": 373.5, "maxX": 539.5, "maxY": 419.0}, "class_id": 1, "box_caption": "defect 0.008", "scores": {"class_score": 0.0079345703125}, "domain": "pixel"}, {"position": {"minX": 375.75, "minY": 591.0, "maxX": 400.25, "maxY": 621.0}, "class_id": 1, "box_caption": "defect 0.008", "scores": {"class_score": 0.0078125}, "domain": "pixel"}, {"position": {"minX": 228.75, "minY": 593.5, "maxX": 367.25, "maxY": 644.5}, "class_id": 1, "box_caption": "defect 0.008", "scores": {"class_score": 0.0078125}, "domain": "pixel"}, {"position": {"minX": 252.75, "minY": 620.5, "maxX": 290.25, "maxY": 642.5}, "class_id": 1, "box_caption": "defect 0.008", "scores": {"class_score": 0.00780487060546875}, "domain": "pixel"}, {"position": {"minX": 380.25, "minY": 594.5, "maxX": 397.75, "maxY": 619.5}, "class_id": 1, "box_caption": "defect 0.008", "scores": {"class_score": 0.007747650146484375}, "domain": "pixel"}, {"position": {"minX": 254.0, "minY": 76.8125, "maxX": 291.0, "maxY": 114.4375}, "class_id": 0, "box_caption": "imbalance 0.008", "scores": {"class_score": 0.007740020751953125}, "domain": "pixel"}, {"position": {"minX": 308.25, "minY": 392.75, "maxX": 320.25, "maxY": 408.75}, "class_id": 0, "box_caption": "imbalance 0.008", "scores": {"class_score": 0.00771331787109375}, "domain": "pixel"}, {"position": {"minX": 530.5, "minY": 19.296875, "maxX": 541.5, "maxY": 32.25}, "class_id": 1, "box_caption": "defect 0.008", "scores": {"class_score": 0.007671356201171875}, "domain": "pixel"}, {"position": {"minX": 566.0, "minY": 618.0, "maxX": 591.0, "maxY": 651.0}, "class_id": 1, "box_caption": "defect 0.008", "scores": {"class_score": 0.0076446533203125}, "domain": "pixel"}, {"position": {"minX": 610.5, "minY": 609.5, "maxX": 650.5, "maxY": 660.5}, "class_id": 0, "box_caption": "imbalance 0.008", "scores": {"class_score": 0.007610321044921875}, "domain": "pixel"}, {"position": {"minX": 421.25, "minY": 554.0, "maxX": 454.75, "maxY": 614.0}, "class_id": 1, "box_caption": "defect 0.008", "scores": {"class_score": 0.007602691650390625}, "domain": "pixel"}, {"position": {"minX": 391.0, "minY": 565.0, "maxX": 455.5, "maxY": 618.0}, "class_id": 0, "box_caption": "imbalance 0.008", "scores": {"class_score": 0.00753021240234375}, "domain": "pixel"}, {"position": {"minX": 556.0, "minY": 164.375, "maxX": 582.0, "maxY": 237.375}, "class_id": 0, "box_caption": "imbalance 0.007", "scores": {"class_score": 0.007457733154296875}, "domain": "pixel"}, {"position": {"minX": 160.5, "minY": 268.75, "maxX": 197.25, "maxY": 301.75}, "class_id": 1, "box_caption": "defect 0.007", "scores": {"class_score": 0.00743865966796875}, "domain": "pixel"}, {"position": {"minX": 263.0, "minY": 15.7578125, "maxX": 278.0, "maxY": 44.375}, "class_id": 0, "box_caption": "imbalance 0.007", "scores": {"class_score": 0.00737762451171875}, "domain": "pixel"}, {"position": {"minX": 315.75, "minY": 17.359375, "maxX": 346.75, "maxY": 60.125}, "class_id": 0, "box_caption": "imbalance 0.007", "scores": {"class_score": 0.007343292236328125}, "domain": "pixel"}, {"position": {"minX": 204.625, "minY": 88.9375, "maxX": 604.0, "maxY": 267.25}, "class_id": 1, "box_caption": "defect 0.007", "scores": {"class_score": 0.00733184814453125}, "domain": "pixel"}, {"position": {"minX": 13.46875, "minY": 608.0, "maxX": 34.625, "maxY": 663.0}, "class_id": 0, "box_caption": "imbalance 0.007", "scores": {"class_score": 0.0072784423828125}, "domain": "pixel"}, {"position": {"minX": 86.8125, "minY": 309.25, "maxX": 99.4375, "maxY": 339.75}, "class_id": 0, "box_caption": "imbalance 0.007", "scores": {"class_score": 0.00726318359375}, "domain": "pixel"}, {"position": {"minX": 481.0, "minY": 105.5, "maxX": 518.0, "maxY": 202.25}, "class_id": 1, "box_caption": "defect 0.007", "scores": {"class_score": 0.007236480712890625}, "domain": "pixel"}, {"position": {"minX": 621.5, "minY": 387.75, "maxX": 655.5, "maxY": 542.0}, "class_id": 1, "box_caption": "defect 0.007", "scores": {"class_score": 0.00722503662109375}, "domain": "pixel"}, {"position": {"minX": 612.0, "minY": 582.5, "maxX": 649.0, "maxY": 661.5}, "class_id": 1, "box_caption": "defect 0.007", "scores": {"class_score": 0.007221221923828125}, "domain": "pixel"}, {"position": {"minX": 584.5, "minY": 606.5, "maxX": 646.5, "maxY": 660.5}, "class_id": 0, "box_caption": "imbalance 0.007", "scores": {"class_score": 0.00717926025390625}, "domain": "pixel"}, {"position": {"minX": 442.75, "minY": 78.5, "maxX": 607.0, "maxY": 270.75}, "class_id": 1, "box_caption": "defect 0.007", "scores": {"class_score": 0.00711822509765625}, "domain": "pixel"}, {"position": {"minX": 514.0, "minY": 146.625, "maxX": 592.0, "maxY": 258.25}, "class_id": 0, "box_caption": "imbalance 0.007", "scores": {"class_score": 0.00705718994140625}, "domain": "pixel"}, {"position": {"minX": 75.6875, "minY": 306.5, "maxX": 118.0625, "maxY": 345.0}, "class_id": 0, "box_caption": "imbalance 0.007", "scores": {"class_score": 0.00704193115234375}, "domain": "pixel"}, {"position": {"minX": 318.0, "minY": 23.5625, "maxX": 353.0, "maxY": 48.0625}, "class_id": 0, "box_caption": "imbalance 0.007", "scores": {"class_score": 0.007007598876953125}, "domain": "pixel"}, {"position": {"minX": 132.125, "minY": 298.25, "maxX": 144.125, "maxY": 323.75}, "class_id": 1, "box_caption": "defect 0.007", "scores": {"class_score": 0.006988525390625}, "domain": "pixel"}, {"position": {"minX": 625.0, "minY": 100.25, "maxX": 654.0, "maxY": 230.25}, "class_id": 0, "box_caption": "imbalance 0.007", "scores": {"class_score": 0.006931304931640625}, "domain": "pixel"}, {"position": {"minX": 374.25, "minY": 554.0, "maxX": 448.25, "maxY": 630.0}, "class_id": 0, "box_caption": "imbalance 0.007", "scores": {"class_score": 0.006927490234375}, "domain": "pixel"}, {"position": {"minX": 193.5, "minY": 52.1875, "maxX": 213.75, "maxY": 75.5625}, "class_id": 1, "box_caption": "defect 0.007", "scores": {"class_score": 0.0069122314453125}, "domain": "pixel"}, {"position": {"minX": 89.375, "minY": 311.0, "maxX": 96.125, "maxY": 323.0}, "class_id": 1, "box_caption": "defect 0.007", "scores": {"class_score": 0.006862640380859375}, "domain": "pixel"}, {"position": {"minX": 471.0, "minY": 600.0, "maxX": 565.0, "maxY": 643.0}, "class_id": 0, "box_caption": "imbalance 0.007", "scores": {"class_score": 0.00684356689453125}, "domain": "pixel"}, {"position": {"minX": 312.5, "minY": 17.09375, "maxX": 337.5, "maxY": 50.40625}, "class_id": 1, "box_caption": "defect 0.007", "scores": {"class_score": 0.006839752197265625}, "domain": "pixel"}, {"position": {"minX": 432.75, "minY": 104.0625, "maxX": 487.25, "maxY": 195.0}, "class_id": 0, "box_caption": "imbalance 0.007", "scores": {"class_score": 0.00681304931640625}, "domain": "pixel"}, {"position": {"minX": 529.5, "minY": 164.625, "maxX": 577.5, "maxY": 239.125}, "class_id": 0, "box_caption": "imbalance 0.007", "scores": {"class_score": 0.006740570068359375}, "domain": "pixel"}, {"position": {"minX": 429.75, "minY": 408.0, "maxX": 640.0, "maxY": 650.0}, "class_id": 1, "box_caption": "defect 0.007", "scores": {"class_score": 0.006732940673828125}, "domain": "pixel"}, {"position": {"minX": 619.0, "minY": 103.625, "maxX": 659.0, "maxY": 260.5}, "class_id": 0, "box_caption": "imbalance 0.007", "scores": {"class_score": 0.006717681884765625}, "domain": "pixel"}, {"position": {"minX": 563.0, "minY": 162.5, "maxX": 584.0, "maxY": 211.5}, "class_id": 0, "box_caption": "imbalance 0.007", "scores": {"class_score": 0.006656646728515625}, "domain": "pixel"}, {"position": {"minX": 436.0, "minY": 151.5, "maxX": 600.0, "maxY": 331.25}, "class_id": 1, "box_caption": "defect 0.007", "scores": {"class_score": 0.006656646728515625}, "domain": "pixel"}, {"position": {"minX": 616.0, "minY": 479.5, "maxX": 652.0, "maxY": 628.5}, "class_id": 1, "box_caption": "defect 0.007", "scores": {"class_score": 0.00653839111328125}, "domain": "pixel"}, {"position": {"minX": 164.375, "minY": 261.5, "maxX": 220.375, "maxY": 290.0}, "class_id": 1, "box_caption": "defect 0.007", "scores": {"class_score": 0.006526947021484375}, "domain": "pixel"}, {"position": {"minX": 19.828125, "minY": 620.5, "maxX": 28.765625, "maxY": 656.5}, "class_id": 1, "box_caption": "defect 0.007", "scores": {"class_score": 0.00650787353515625}, "domain": "pixel"}, {"position": {"minX": 553.5, "minY": 243.25, "maxX": 593.5, "maxY": 303.75}, "class_id": 1, "box_caption": "defect 0.007", "scores": {"class_score": 0.006500244140625}, "domain": "pixel"}, {"position": {"minX": 419.0, "minY": 560.0, "maxX": 440.5, "maxY": 600.0}, "class_id": 1, "box_caption": "defect 0.006", "scores": {"class_score": 0.006496429443359375}, "domain": "pixel"}, {"position": {"minX": 489.0, "minY": 110.5, "maxX": 505.5, "maxY": 165.75}, "class_id": 1, "box_caption": "defect 0.006", "scores": {"class_score": 0.00649261474609375}, "domain": "pixel"}, {"position": {"minX": 466.5, "minY": 83.5, "maxX": 639.5, "maxY": 645.5}, "class_id": 1, "box_caption": "defect 0.006", "scores": {"class_score": 0.006435394287109375}, "domain": "pixel"}, {"position": {"minX": 50.875, "minY": 415.75, "maxX": 388.0, "maxY": 589.5}, "class_id": 1, "box_caption": "defect 0.006", "scores": {"class_score": 0.0064239501953125}, "domain": "pixel"}, {"position": {"minX": 169.375, "minY": 270.0, "maxX": 201.875, "maxY": 296.0}, "class_id": 0, "box_caption": "imbalance 0.006", "scores": {"class_score": 0.006420135498046875}, "domain": "pixel"}, {"position": {"minX": 558.0, "minY": 159.75, "maxX": 586.0, "maxY": 224.0}, "class_id": 1, "box_caption": "defect 0.006", "scores": {"class_score": 0.00640869140625}, "domain": "pixel"}, {"position": {"minX": 412.5, "minY": 103.5, "maxX": 504.5, "maxY": 186.5}, "class_id": 1, "box_caption": "defect 0.006", "scores": {"class_score": 0.006397247314453125}, "domain": "pixel"}, {"position": {"minX": 616.0, "minY": 479.5, "maxX": 652.0, "maxY": 628.5}, "class_id": 0, "box_caption": "imbalance 0.006", "scores": {"class_score": 0.006397247314453125}, "domain": "pixel"}, {"position": {"minX": 256.5, "minY": 614.0, "maxX": 291.0, "maxY": 638.0}, "class_id": 1, "box_caption": "defect 0.006", "scores": {"class_score": 0.006366729736328125}, "domain": "pixel"}, {"position": {"minX": 384.5, "minY": 354.5, "maxX": 396.0, "maxY": 370.0}, "class_id": 0, "box_caption": "imbalance 0.006", "scores": {"class_score": 0.006317138671875}, "domain": "pixel"}, {"position": {"minX": 272.0, "minY": 500.0, "maxX": 294.0, "maxY": 552.0}, "class_id": 1, "box_caption": "defect 0.006", "scores": {"class_score": 0.00630950927734375}, "domain": "pixel"}, {"position": {"minX": 447.75, "minY": 165.75, "maxX": 510.75, "maxY": 238.0}, "class_id": 0, "box_caption": "imbalance 0.006", "scores": {"class_score": 0.006259918212890625}, "domain": "pixel"}, {"position": {"minX": 548.0, "minY": 161.0, "maxX": 594.0, "maxY": 238.0}, "class_id": 1, "box_caption": "defect 0.006", "scores": {"class_score": 0.00614166259765625}, "domain": "pixel"}, {"position": {"minX": 528.5, "minY": 20.40625, "maxX": 539.5, "maxY": 30.5}, "class_id": 1, "box_caption": "defect 0.006", "scores": {"class_score": 0.006137847900390625}, "domain": "pixel"}, {"position": {"minX": 500.25, "minY": 217.25, "maxX": 574.0, "maxY": 317.75}, "class_id": 0, "box_caption": "imbalance 0.006", "scores": {"class_score": 0.006076812744140625}, "domain": "pixel"}, {"position": {"minX": 183.25, "minY": 47.6875, "maxX": 212.75, "maxY": 91.3125}, "class_id": 0, "box_caption": "imbalance 0.006", "scores": {"class_score": 0.00606536865234375}, "domain": "pixel"}, {"position": {"minX": 481.0, "minY": 105.5, "maxX": 518.0, "maxY": 202.25}, "class_id": 0, "box_caption": "imbalance 0.006", "scores": {"class_score": 0.00603485107421875}, "domain": "pixel"}, {"position": {"minX": 88.625, "minY": 303.5, "maxX": 121.25, "maxY": 348.5}, "class_id": 1, "box_caption": "defect 0.006", "scores": {"class_score": 0.006023406982421875}, "domain": "pixel"}, {"position": {"minX": 610.5, "minY": 546.5, "maxX": 651.5, "maxY": 665.5}, "class_id": 1, "box_caption": "defect 0.006", "scores": {"class_score": 0.00601959228515625}, "domain": "pixel"}, {"position": {"minX": 607.0, "minY": 18.65625, "maxX": 650.0, "maxY": 97.25}, "class_id": 0, "box_caption": "imbalance 0.006", "scores": {"class_score": 0.0059967041015625}, "domain": "pixel"}, {"position": {"minX": 361.5, "minY": 578.5, "maxX": 450.5, "maxY": 631.5}, "class_id": 0, "box_caption": "imbalance 0.006", "scores": {"class_score": 0.005992889404296875}, "domain": "pixel"}, {"position": {"minX": 467.25, "minY": 166.25, "maxX": 504.25, "maxY": 233.5}, "class_id": 0, "box_caption": "imbalance 0.006", "scores": {"class_score": 0.00597381591796875}, "domain": "pixel"}, {"position": {"minX": 382.75, "minY": 352.0, "maxX": 404.25, "maxY": 371.0}, "class_id": 1, "box_caption": "defect 0.006", "scores": {"class_score": 0.00592041015625}, "domain": "pixel"}, {"position": {"minX": 421.0, "minY": 112.5, "maxX": 479.0, "maxY": 219.5}, "class_id": 1, "box_caption": "defect 0.006", "scores": {"class_score": 0.005908966064453125}, "domain": "pixel"}, {"position": {"minX": 438.0, "minY": 586.5, "maxX": 542.0, "maxY": 663.5}, "class_id": 0, "box_caption": "imbalance 0.006", "scores": {"class_score": 0.00589752197265625}, "domain": "pixel"}, {"position": {"minX": 334.0, "minY": 132.375, "maxX": 554.5, "maxY": 289.5}, "class_id": 1, "box_caption": "defect 0.006", "scores": {"class_score": 0.005889892578125}, "domain": "pixel"}, {"position": {"minX": 313.25, "minY": 54.5, "maxX": 343.25, "maxY": 91.5}, "class_id": 0, "box_caption": "imbalance 0.006", "scores": {"class_score": 0.0058441162109375}, "domain": "pixel"}, {"position": {"minX": 519.5, "minY": 278.5, "maxX": 565.5, "maxY": 315.5}, "class_id": 1, "box_caption": "defect 0.006", "scores": {"class_score": 0.005832672119140625}, "domain": "pixel"}, {"position": {"minX": 539.5, "minY": 328.5, "maxX": 592.5, "maxY": 427.5}, "class_id": 0, "box_caption": "imbalance 0.006", "scores": {"class_score": 0.005828857421875}, "domain": "pixel"}, {"position": {"minX": 607.5, "minY": 96.9375, "maxX": 660.5, "maxY": 326.25}, "class_id": 1, "box_caption": "defect 0.006", "scores": {"class_score": 0.005786895751953125}, "domain": "pixel"}, {"position": {"minX": 263.5, "minY": 85.4375, "maxX": 287.5, "maxY": 112.6875}, "class_id": 0, "box_caption": "imbalance 0.006", "scores": {"class_score": 0.00574493408203125}, "domain": "pixel"}, {"position": {"minX": 547.0, "minY": 250.125, "maxX": 582.0, "maxY": 310.0}, "class_id": 0, "box_caption": "imbalance 0.006", "scores": {"class_score": 0.0057373046875}, "domain": "pixel"}, {"position": {"minX": 254.0, "minY": 76.8125, "maxX": 291.0, "maxY": 114.4375}, "class_id": 1, "box_caption": "defect 0.006", "scores": {"class_score": 0.005710601806640625}, "domain": "pixel"}, {"position": {"minX": 619.0, "minY": 122.6875, "maxX": 648.0, "maxY": 215.5}, "class_id": 0, "box_caption": "imbalance 0.006", "scores": {"class_score": 0.005687713623046875}, "domain": "pixel"}, {"position": {"minX": 614.0, "minY": 448.5, "maxX": 656.0, "maxY": 590.5}, "class_id": 0, "box_caption": "imbalance 0.006", "scores": {"class_score": 0.00568389892578125}, "domain": "pixel"}, {"position": {"minX": 310.25, "minY": 26.21875, "maxX": 326.25, "maxY": 67.0}, "class_id": 1, "box_caption": "defect 0.006", "scores": {"class_score": 0.005649566650390625}, "domain": "pixel"}, {"position": {"minX": 309.75, "minY": 390.75, "maxX": 319.25, "maxY": 413.25}, "class_id": 0, "box_caption": "imbalance 0.006", "scores": {"class_score": 0.005645751953125}, "domain": "pixel"}, {"position": {"minX": 521.0, "minY": 259.25, "maxX": 552.0, "maxY": 323.25}, "class_id": 1, "box_caption": "defect 0.006", "scores": {"class_score": 0.00562286376953125}, "domain": "pixel"}, {"position": {"minX": 148.375, "minY": 514.0, "maxX": 202.875, "maxY": 549.0}, "class_id": 0, "box_caption": "imbalance 0.006", "scores": {"class_score": 0.005619049072265625}, "domain": "pixel"}, {"position": {"minX": 171.5, "minY": 509.75, "maxX": 183.5, "maxY": 519.5}, "class_id": 0, "box_caption": "imbalance 0.006", "scores": {"class_score": 0.005611419677734375}, "domain": "pixel"}, {"position": {"minX": 632.5, "minY": 100.625, "maxX": 654.5, "maxY": 200.375}, "class_id": 1, "box_caption": "defect 0.006", "scores": {"class_score": 0.00560760498046875}, "domain": "pixel"}, {"position": {"minX": 307.0, "minY": 24.65625, "maxX": 354.0, "maxY": 72.625}, "class_id": 0, "box_caption": "imbalance 0.006", "scores": {"class_score": 0.005558013916015625}, "domain": "pixel"}, {"position": {"minX": 614.0, "minY": 24.90625, "maxX": 651.0, "maxY": 150.5}, "class_id": 0, "box_caption": "imbalance 0.006", "scores": {"class_score": 0.005504608154296875}, "domain": "pixel"}, {"position": {"minX": 431.5, "minY": 605.0, "maxX": 451.0, "maxY": 666.0}, "class_id": 1, "box_caption": "defect 0.005", "scores": {"class_score": 0.005496978759765625}, "domain": "pixel"}, {"position": {"minX": 172.5, "minY": 268.25, "maxX": 182.5, "maxY": 296.75}, "class_id": 1, "box_caption": "defect 0.005", "scores": {"class_score": 0.00547027587890625}, "domain": "pixel"}, {"position": {"minX": 76.1875, "minY": 88.0, "maxX": 278.0, "maxY": 378.5}, "class_id": 1, "box_caption": "defect 0.005", "scores": {"class_score": 0.00543975830078125}, "domain": "pixel"}, {"position": {"minX": 526.5, "minY": 15.8125, "maxX": 538.5, "maxY": 43.5625}, "class_id": 0, "box_caption": "imbalance 0.005", "scores": {"class_score": 0.005428314208984375}, "domain": "pixel"}, {"position": {"minX": 11.875, "minY": 81.8125, "maxX": 470.0, "maxY": 279.25}, "class_id": 1, "box_caption": "defect 0.005", "scores": {"class_score": 0.005428314208984375}, "domain": "pixel"}, {"position": {"minX": 496.5, "minY": 136.25, "maxX": 611.5, "maxY": 300.75}, "class_id": 1, "box_caption": "defect 0.005", "scores": {"class_score": 0.005413055419921875}, "domain": "pixel"}, {"position": {"minX": 390.5, "minY": 553.0, "maxX": 461.0, "maxY": 636.0}, "class_id": 1, "box_caption": "defect 0.005", "scores": {"class_score": 0.005390167236328125}, "domain": "pixel"}, {"position": {"minX": 490.0, "minY": 121.5, "maxX": 508.0, "maxY": 158.5}, "class_id": 1, "box_caption": "defect 0.005", "scores": {"class_score": 0.0053863525390625}, "domain": "pixel"}, {"position": {"minX": 623.0, "minY": 368.75, "maxX": 651.0, "maxY": 487.75}, "class_id": 0, "box_caption": "imbalance 0.005", "scores": {"class_score": 0.00537872314453125}, "domain": "pixel"}, {"position": {"minX": 558.5, "minY": 214.375, "maxX": 580.5, "maxY": 267.5}, "class_id": 0, "box_caption": "imbalance 0.005", "scores": {"class_score": 0.00533294677734375}, "domain": "pixel"}, {"position": {"minX": 619.5, "minY": 43.46875, "maxX": 653.5, "maxY": 163.25}, "class_id": 1, "box_caption": "defect 0.005", "scores": {"class_score": 0.005321502685546875}, "domain": "pixel"}, {"position": {"minX": 595.5, "minY": 25.75, "maxX": 649.5, "maxY": 579.0}, "class_id": 1, "box_caption": "defect 0.005", "scores": {"class_score": 0.005279541015625}, "domain": "pixel"}, {"position": {"minX": 113.0, "minY": 290.25, "maxX": 142.0, "maxY": 326.25}, "class_id": 0, "box_caption": "imbalance 0.005", "scores": {"class_score": 0.00527191162109375}, "domain": "pixel"}, {"position": {"minX": 503.0, "minY": 165.625, "maxX": 563.0, "maxY": 267.0}, "class_id": 0, "box_caption": "imbalance 0.005", "scores": {"class_score": 0.005252838134765625}, "domain": "pixel"}, {"position": {"minX": 427.5, "minY": 91.75, "maxX": 524.0, "maxY": 248.75}, "class_id": 1, "box_caption": "defect 0.005", "scores": {"class_score": 0.0052490234375}, "domain": "pixel"}, {"position": {"minX": 113.0, "minY": 290.25, "maxX": 142.0, "maxY": 326.25}, "class_id": 1, "box_caption": "defect 0.005", "scores": {"class_score": 0.00522613525390625}, "domain": "pixel"}, {"position": {"minX": 425.5, "minY": 610.0, "maxX": 463.0, "maxY": 657.0}, "class_id": 0, "box_caption": "imbalance 0.005", "scores": {"class_score": 0.005222320556640625}, "domain": "pixel"}, {"position": {"minX": 396.25, "minY": 81.75, "maxX": 534.5, "maxY": 225.75}, "class_id": 1, "box_caption": "defect 0.005", "scores": {"class_score": 0.005214691162109375}, "domain": "pixel"}, {"position": {"minX": 444.5, "minY": 120.25, "maxX": 589.5, "maxY": 397.75}, "class_id": 1, "box_caption": "defect 0.005", "scores": {"class_score": 0.00518035888671875}, "domain": "pixel"}, {"position": {"minX": 277.25, "minY": 502.75, "maxX": 296.75, "maxY": 548.0}, "class_id": 1, "box_caption": "defect 0.005", "scores": {"class_score": 0.005153656005859375}, "domain": "pixel"}, {"position": {"minX": 475.5, "minY": 373.5, "maxX": 539.5, "maxY": 419.0}, "class_id": 0, "box_caption": "imbalance 0.005", "scores": {"class_score": 0.00514984130859375}, "domain": "pixel"}, {"position": {"minX": 530.0, "minY": 253.25, "maxX": 566.0, "maxY": 313.25}, "class_id": 0, "box_caption": "imbalance 0.005", "scores": {"class_score": 0.0051422119140625}, "domain": "pixel"}, {"position": {"minX": 424.5, "minY": 606.5, "maxX": 627.5, "maxY": 659.5}, "class_id": 1, "box_caption": "defect 0.005", "scores": {"class_score": 0.005115509033203125}, "domain": "pixel"}, {"position": {"minX": 521.0, "minY": 259.25, "maxX": 552.0, "maxY": 323.25}, "class_id": 0, "box_caption": "imbalance 0.005", "scores": {"class_score": 0.00510406494140625}, "domain": "pixel"}, {"position": {"minX": 83.5, "minY": 314.25, "maxX": 104.0, "maxY": 335.75}, "class_id": 1, "box_caption": "defect 0.005", "scores": {"class_score": 0.005096435546875}, "domain": "pixel"}, {"position": {"minX": 209.25, "minY": 51.125, "maxX": 588.0, "maxY": 128.375}, "class_id": 1, "box_caption": "defect 0.005", "scores": {"class_score": 0.005092620849609375}, "domain": "pixel"}, {"position": {"minX": 180.375, "minY": 261.5, "maxX": 204.375, "maxY": 286.5}, "class_id": 0, "box_caption": "imbalance 0.005", "scores": {"class_score": 0.005084991455078125}, "domain": "pixel"}, {"position": {"minX": 405.5, "minY": 547.5, "maxX": 444.5, "maxY": 627.5}, "class_id": 0, "box_caption": "imbalance 0.005", "scores": {"class_score": 0.005077362060546875}, "domain": "pixel"}, {"position": {"minX": 295.0, "minY": 615.5, "maxX": 307.0, "maxY": 636.5}, "class_id": 1, "box_caption": "defect 0.005", "scores": {"class_score": 0.00505828857421875}, "domain": "pixel"}, {"position": {"minX": 511.25, "minY": 237.125, "maxX": 551.0, "maxY": 312.0}, "class_id": 0, "box_caption": "imbalance 0.005", "scores": {"class_score": 0.00502777099609375}, "domain": "pixel"}, {"position": {"minX": 208.625, "minY": 603.5, "maxX": 325.0, "maxY": 648.5}, "class_id": 1, "box_caption": "defect 0.005", "scores": {"class_score": 0.00502777099609375}, "domain": "pixel"}, {"position": {"minX": 561.0, "minY": 612.5, "maxX": 586.0, "maxY": 650.5}, "class_id": 1, "box_caption": "defect 0.005", "scores": {"class_score": 0.005016326904296875}, "domain": "pixel"}, {"position": {"minX": 618.0, "minY": 335.25, "maxX": 651.0, "maxY": 452.25}, "class_id": 0, "box_caption": "imbalance 0.005", "scores": {"class_score": 0.00501251220703125}, "domain": "pixel"}, {"position": {"minX": 575.0, "minY": 555.5, "maxX": 653.0, "maxY": 650.5}, "class_id": 1, "box_caption": "defect 0.005", "scores": {"class_score": 0.005008697509765625}, "domain": "pixel"}, {"position": {"minX": 103.0, "minY": 306.75, "maxX": 140.875, "maxY": 346.75}, "class_id": 1, "box_caption": "defect 0.005", "scores": {"class_score": 0.004978179931640625}, "domain": "pixel"}, {"position": {"minX": 267.75, "minY": 614.5, "maxX": 291.25, "maxY": 642.5}, "class_id": 0, "box_caption": "imbalance 0.005", "scores": {"class_score": 0.004974365234375}, "domain": "pixel"}, {"position": {"minX": 565.5, "minY": 166.25, "maxX": 589.5, "maxY": 235.75}, "class_id": 0, "box_caption": "imbalance 0.005", "scores": {"class_score": 0.004974365234375}, "domain": "pixel"}, {"position": {"minX": 192.625, "minY": 350.75, "maxX": 330.0, "maxY": 501.75}, "class_id": 1, "box_caption": "defect 0.005", "scores": {"class_score": 0.00496673583984375}, "domain": "pixel"}, {"position": {"minX": 253.375, "minY": 510.75, "maxX": 306.25, "maxY": 549.0}, "class_id": 1, "box_caption": "defect 0.005", "scores": {"class_score": 0.004955291748046875}, "domain": "pixel"}, {"position": {"minX": 312.5, "minY": 17.09375, "maxX": 337.5, "maxY": 50.40625}, "class_id": 0, "box_caption": "imbalance 0.005", "scores": {"class_score": 0.004947662353515625}, "domain": "pixel"}, {"position": {"minX": 326.0, "minY": 113.0, "maxX": 561.0, "maxY": 236.25}, "class_id": 1, "box_caption": "defect 0.005", "scores": {"class_score": 0.00494384765625}, "domain": "pixel"}, {"position": {"minX": 625.5, "minY": 121.0625, "maxX": 643.5, "maxY": 185.5}, "class_id": 0, "box_caption": "imbalance 0.005", "scores": {"class_score": 0.0049285888671875}, "domain": "pixel"}, {"position": {"minX": 548.5, "minY": 565.5, "maxX": 631.5, "maxY": 641.5}, "class_id": 1, "box_caption": "defect 0.005", "scores": {"class_score": 0.004917144775390625}, "domain": "pixel"}, {"position": {"minX": 569.5, "minY": 356.5, "maxX": 597.5, "maxY": 427.0}, "class_id": 0, "box_caption": "imbalance 0.005", "scores": {"class_score": 0.00490570068359375}, "domain": "pixel"}, {"position": {"minX": 554.0, "minY": 624.0, "maxX": 601.0, "maxY": 655.0}, "class_id": 1, "box_caption": "defect 0.005", "scores": {"class_score": 0.00487518310546875}, "domain": "pixel"}, {"position": {"minX": 418.0, "minY": 139.25, "maxX": 559.5, "maxY": 283.75}, "class_id": 1, "box_caption": "defect 0.005", "scores": {"class_score": 0.00487518310546875}, "domain": "pixel"}, {"position": {"minX": 188.0, "minY": 526.5, "maxX": 201.75, "maxY": 540.5}, "class_id": 1, "box_caption": "defect 0.005", "scores": {"class_score": 0.004856109619140625}, "domain": "pixel"}, {"position": {"minX": 253.375, "minY": 510.75, "maxX": 306.25, "maxY": 549.0}, "class_id": 0, "box_caption": "imbalance 0.005", "scores": {"class_score": 0.004848480224609375}, "domain": "pixel"}, {"position": {"minX": 381.0, "minY": 355.0, "maxX": 392.0, "maxY": 375.0}, "class_id": 1, "box_caption": "defect 0.005", "scores": {"class_score": 0.004772186279296875}, "domain": "pixel"}, {"position": {"minX": 551.0, "minY": 607.5, "maxX": 580.0, "maxY": 643.5}, "class_id": 1, "box_caption": "defect 0.005", "scores": {"class_score": 0.00475311279296875}, "domain": "pixel"}, {"position": {"minX": 297.25, "minY": 380.25, "maxX": 342.25, "maxY": 429.75}, "class_id": 0, "box_caption": "imbalance 0.005", "scores": {"class_score": 0.004730224609375}, "domain": "pixel"}, {"position": {"minX": 93.5625, "minY": 306.5, "maxX": 146.0, "maxY": 368.5}, "class_id": 1, "box_caption": "defect 0.005", "scores": {"class_score": 0.0047149658203125}, "domain": "pixel"}, {"position": {"minX": 447.5, "minY": 397.0, "maxX": 529.5, "maxY": 519.5}, "class_id": 0, "box_caption": "imbalance 0.005", "scores": {"class_score": 0.0047149658203125}, "domain": "pixel"}, {"position": {"minX": 109.0, "minY": 37.0625, "maxX": 138.0, "maxY": 99.6875}, "class_id": 0, "box_caption": "imbalance 0.005", "scores": {"class_score": 0.0047149658203125}, "domain": "pixel"}, {"position": {"minX": 22.015625, "minY": 30.125, "maxX": 42.75, "maxY": 78.25}, "class_id": 0, "box_caption": "imbalance 0.005", "scores": {"class_score": 0.004695892333984375}, "domain": "pixel"}, {"position": {"minX": 624.0, "minY": 125.6875, "maxX": 659.0, "maxY": 306.25}, "class_id": 1, "box_caption": "defect 0.005", "scores": {"class_score": 0.004688262939453125}, "domain": "pixel"}, {"position": {"minX": 549.0, "minY": 158.75, "maxX": 605.0, "maxY": 273.75}, "class_id": 0, "box_caption": "imbalance 0.005", "scores": {"class_score": 0.0046844482421875}, "domain": "pixel"}, {"position": {"minX": 610.5, "minY": 546.5, "maxX": 651.5, "maxY": 665.5}, "class_id": 0, "box_caption": "imbalance 0.005", "scores": {"class_score": 0.0046844482421875}, "domain": "pixel"}, {"position": {"minX": 193.5, "minY": 52.1875, "maxX": 213.75, "maxY": 75.5625}, "class_id": 0, "box_caption": "imbalance 0.005", "scores": {"class_score": 0.004680633544921875}, "domain": "pixel"}, {"position": {"minX": 546.0, "minY": 213.0, "maxX": 618.0, "maxY": 319.0}, "class_id": 0, "box_caption": "imbalance 0.005", "scores": {"class_score": 0.004642486572265625}, "domain": "pixel"}, {"position": {"minX": 352.5, "minY": 623.0, "maxX": 450.5, "maxY": 666.0}, "class_id": 1, "box_caption": "defect 0.005", "scores": {"class_score": 0.004638671875}, "domain": "pixel"}, {"position": {"minX": 263.5, "minY": 85.4375, "maxX": 287.5, "maxY": 112.6875}, "class_id": 1, "box_caption": "defect 0.005", "scores": {"class_score": 0.004627227783203125}, "domain": "pixel"}, {"position": {"minX": 25.375, "minY": 28.40625, "maxX": 80.5625, "maxY": 86.25}, "class_id": 0, "box_caption": "imbalance 0.005", "scores": {"class_score": 0.004619598388671875}, "domain": "pixel"}, {"position": {"minX": 163.375, "minY": 506.75, "maxX": 191.125, "maxY": 527.5}, "class_id": 0, "box_caption": "imbalance 0.005", "scores": {"class_score": 0.00461578369140625}, "domain": "pixel"}, {"position": {"minX": 371.0, "minY": 17.4375, "maxX": 376.0, "maxY": 34.6875}, "class_id": 1, "box_caption": "defect 0.005", "scores": {"class_score": 0.004611968994140625}, "domain": "pixel"}, {"position": {"minX": 524.5, "minY": 13.828125, "maxX": 545.5, "maxY": 46.3125}, "class_id": 0, "box_caption": "imbalance 0.005", "scores": {"class_score": 0.004611968994140625}, "domain": "pixel"}, {"position": {"minX": 411.5, "minY": 600.0, "maxX": 594.5, "maxY": 641.0}, "class_id": 1, "box_caption": "defect 0.005", "scores": {"class_score": 0.004573822021484375}, "domain": "pixel"}, {"position": {"minX": 482.0, "minY": 165.75, "maxX": 499.5, "maxY": 230.25}, "class_id": 1, "box_caption": "defect 0.005", "scores": {"class_score": 0.00455474853515625}, "domain": "pixel"}, {"position": {"minX": 609.0, "minY": 25.09375, "maxX": 652.0, "maxY": 124.0}, "class_id": 1, "box_caption": "defect 0.005", "scores": {"class_score": 0.004543304443359375}, "domain": "pixel"}], "class_labels": {"0": "imbalance", "1": "defect"}}